cppjieba_py_dat/__init__.py
cppjieba_py_dat/bindings.cpython-313-i386-linux-gnu.so
cppjieba_py_dat/bindings.pyi
cppjieba_py_dat/cpp/bindings.cpp
cppjieba_py_dat/cpp/cppjieba/darts-clone/darts.h
cppjieba_py_dat/cpp/cppjieba/include/cppjieba/DatTrie.hpp
cppjieba_py_dat/cpp/cppjieba/include/cppjieba/DictTrie.hpp
cppjieba_py_dat/cpp/cppjieba/include/cppjieba/FullSegment.hpp
cppjieba_py_dat/cpp/cppjieba/include/cppjieba/HMMModel.hpp
cppjieba_py_dat/cpp/cppjieba/include/cppjieba/HMMSegment.hpp
cppjieba_py_dat/cpp/cppjieba/include/cppjieba/Jieba.hpp
cppjieba_py_dat/cpp/cppjieba/include/cppjieba/KeywordExtractor.hpp
cppjieba_py_dat/cpp/cppjieba/include/cppjieba/MPSegment.hpp
cppjieba_py_dat/cpp/cppjieba/include/cppjieba/MixSegment.hpp
cppjieba_py_dat/cpp/cppjieba/include/cppjieba/PosTagger.hpp
cppjieba_py_dat/cpp/cppjieba/include/cppjieba/PreFilter.hpp
cppjieba_py_dat/cpp/cppjieba/include/cppjieba/QuerySegment.hpp
cppjieba_py_dat/cpp/cppjieba/include/cppjieba/SegmentBase.hpp
cppjieba_py_dat/cpp/cppjieba/include/cppjieba/SegmentTagged.hpp
cppjieba_py_dat/cpp/cppjieba/include/cppjieba/TextRankExtractor.hpp
cppjieba_py_dat/cpp/cppjieba/include/cppjieba/Unicode.hpp
cppjieba_py_dat/cpp/cppjieba/limonp/ArgvContext.hpp
cppjieba_py_dat/cpp/cppjieba/limonp/BlockingQueue.hpp
cppjieba_py_dat/cpp/cppjieba/limonp/BoundedBlockingQueue.hpp
cppjieba_py_dat/cpp/cppjieba/limonp/BoundedQueue.hpp
cppjieba_py_dat/cpp/cppjieba/limonp/Closure.hpp
cppjieba_py_dat/cpp/cppjieba/limonp/Colors.hpp
cppjieba_py_dat/cpp/cppjieba/limonp/Condition.hpp
cppjieba_py_dat/cpp/cppjieba/limonp/Config.hpp
cppjieba_py_dat/cpp/cppjieba/limonp/FileLock.hpp
cppjieba_py_dat/cpp/cppjieba/limonp/ForcePublic.hpp
cppjieba_py_dat/cpp/cppjieba/limonp/LocalVector.hpp
cppjieba_py_dat/cpp/cppjieba/limonp/Logging.hpp
cppjieba_py_dat/cpp/cppjieba/limonp/Md5.cpp
cppjieba_py_dat/cpp/cppjieba/limonp/Md5.hpp
cppjieba_py_dat/cpp/cppjieba/limonp/MutexLock.hpp
cppjieba_py_dat-0.0.1.dist-info/METADATA
cppjieba_py_dat-0.0.1.dist-info/WHEEL
cppjieba_py_dat-0.0.1.dist-info/top_level.txt
cppjieba_py_dat-0.0.1.dist-info/RECORD
cppjieba_py_dat-0.0.1.dist-info/licenses/LICENSE
