Metadata-Version: 2.1
Name: cppjieba-py-dat
Version: 0.0.1
Summary: 内存优化的 CppJieba Python 绑定 (基于 DAT)
Author-email: xiaosu <xiaosu-1009@qq.com>
License: MIT License
Project-URL: Homepage, https://github.com/xiaosuyyds/cppjieba-py-dat
Project-URL: Bug Tracker, https://github.com/xiaosuyyds/cppjieba-py-dat/issues
Classifier: Development Status :: 4 - Beta
Classifier: Programming Language :: Python :: 3
Classifier: Programming Language :: Python :: 3.8
Classifier: Programming Language :: Python :: 3.9
Classifier: Programming Language :: Python :: 3.10
Classifier: Programming Language :: Python :: 3.11
Classifier: Programming Language :: Python :: 3.12
Classifier: Programming Language :: C++
Classifier: Operating System :: OS Independent
Classifier: Topic :: Text Processing :: Linguistic
Classifier: Intended Audience :: Developers
Requires-Python: >=3.8
License-File: LICENSE
Requires-Dist: appdirs>=1.4.0
